{"word":"rule","count":6}
{"word":"sacrifice","count":6}
{"word":"safety","count":6}
{"word":"sailor","count":6}
{"word":"sang","count":6}
{"word":"september","count":6}
{"word":"services","count":6}
{"word":"sharing","count":6}
{"word":"ship","count":6}
{"word":"shooting","count":6}
{"word":"shoulders","count":6}
{"word":"silly","count":6}
{"word":"singing","count":6}
{"word":"situated","count":6}
{"word":"slighted","count":6}
{"word":"slightly","count":6}
{"word":"sneezing","count":6}
{"word":"somewhat","count":6}
{"word":"sophy","count":6}
{"word":"speedy","count":6}
{"word":"spending","count":6}
{"word":"sprung","count":6}
{"word":"staid","count":6}
{"word":"stepping","count":6}
{"word":"stretched","count":6}
{"word":"strike","count":6}
{"word":"suitable","count":6}
{"word":"sun","count":6}
{"word":"surgeon","count":6}
{"word":"suspicions","count":6}
{"word":"symptom","count":6}
{"word":"tale","count":6}
{"word":"talents","count":6}
{"word":"taunton","count":6}
{"word":"temptation","count":6}
{"word":"tendency","count":6}
{"word":"thither","count":6}
{"word":"thoughtfully","count":6}
{"word":"thoughtfulness","count":6}
{"word":"thursday","count":6}
{"word":"treating","count":6}
{"word":"trembling","count":6}
{"word":"trifle","count":6}
{"word":"trifling","count":6}
{"word":"troublesome","count":6}
