{"word":"confidant","count":1}
{"word":"confidante","count":1}
{"word":"confide","count":1}
{"word":"confided","count":1}
{"word":"confiding","count":1}
{"word":"conflicts","count":1}
{"word":"conform","count":1}
{"word":"conforming","count":1}
{"word":"conformity","count":1}
{"word":"confound","count":1}
{"word":"confounded","count":1}
{"word":"confusedly","count":1}
{"word":"conger","count":1}
{"word":"congratulating","count":1}
{"word":"conjecturing","count":1}
{"word":"conjunctions","count":1}
{"word":"conjure","count":1}
{"word":"conjurer","count":1}
{"word":"connecting","count":1}
{"word":"conning","count":1}
{"word":"connoisseur","count":1}
{"word":"connoisseurship","count":1}
{"word":"conscientiously","count":1}
{"word":"consciously","count":1}
{"word":"consigned","count":1}
{"word":"consistency","count":1}
{"word":"consists","count":1}
{"word":"consoling","count":1}
{"word":"conspicuous","count":1}
{"word":"conspired","count":1}
{"word":"constantia","count":1}
{"word":"consternation","count":1}
{"word":"constitutional","count":1}
{"word":"constrained","count":1}
{"word":"constructed","count":1}
{"word":"construction","count":1}
{"word":"consultations","count":1}
{"word":"consulting","count":1}
{"word":"consumed","count":1}
{"word":"consumption","count":1}
{"word":"contemplating","count":1}
{"word":"contended","count":1}
{"word":"contiguous","count":1}
{"word":"continuation","count":1}
{"word":"contractions","count":1}
{"word":"contribute","count":1}
